kintex/__init__.py
kintex/_constants.py
kintex/clippings.py
kintex-0.1.0.dist-info/WHEEL
kintex-0.1.0.dist-info/METADATA
kintex-0.1.0.dist-info/RECORD
