Metadata-Version: 2.3
Name: kintex
Version: 0.1.0
Summary: A framework to beautify your kindle notes.
Author: Connor Hibble, Matt Humphrey
Author-email: Connor Hibble <dev@hibble.com>, Matt Humphrey <mhumphrey9@hotmail.com>
Requires-Dist: polars>=1.24.0
Requires-Dist: pyarrow>=21.0.0
Requires-Python: >=3.10
